mgwas_data_exploration_app/__init__.py
mgwas_data_exploration_app/main.py
mgwas_data_exploration_app/manhattan.py
mgwas_data_exploration_app/plotting.py
mgwas_data_exploration_app/templates/config.json
mgwas_data_exploration_app/templates/favicon.svg
mgwas_data_exploration_app/templates/overview.css
mgwas_data_exploration_app/templates/overview.html
mgwas_data_exploration_app/templates/overview.js
mgwas_data_exploration_app/templates/trait.css
mgwas_data_exploration_app/templates/trait.html
mgwas_data_exploration_app/templates/trait.js
mgwas_data_exploration_app/utils.py
mgwas_data_exploration_app-0.1.1.dist-info/LICENSE
mgwas_data_exploration_app-0.1.1.dist-info/METADATA
mgwas_data_exploration_app-0.1.1.dist-info/WHEEL
mgwas_data_exploration_app-0.1.1.dist-info/entry_points.txt
mgwas_data_exploration_app-0.1.1.dist-info/RECORD
