Metadata-Version: 2.1
Name: mgwas-data-exploration-app
Version: 0.1.1
Summary: Data exploration app for large phenotypic datasets analyzed using mGWAS, originally developed for Scoary2
Author: MrTomRod
Author-email: roder.thomas@gmail.com
Requires-Python: >=3.10
Classifier: Programming Language :: Python :: 3
Classifier: Programming Language :: Python :: 3.10
Classifier: Programming Language :: Python :: 3.11
Classifier: Programming Language :: Python :: 3.12
Requires-Dist: matplotlib (>=3.5.2)
Requires-Dist: pandas (>=2.1.1)
Requires-Dist: scipy (>=1.7.3)
